neurocollage/__init__.py
neurocollage/cli.py
neurocollage/collage.py
neurocollage/exceptions.py
neurocollage/loader.py
neurocollage/mesh_helper.py
neurocollage/planes.py
neurocollage/utils.py
neurocollage/version.py
neurocollage/planes_utils/__init__.py
neurocollage/planes_utils/maths.py
neurocollage/planes_utils/planes.py
neurocollage-0.3.7.dist-info/AUTHORS.md
neurocollage-0.3.7.dist-info/LICENSE.txt
neurocollage-0.3.7.dist-info/METADATA
neurocollage-0.3.7.dist-info/WHEEL
neurocollage-0.3.7.dist-info/entry_points.txt
neurocollage-0.3.7.dist-info/top_level.txt
neurocollage-0.3.7.dist-info/RECORD
