Metadata-Version: 2.1
Name: neurocollage
Version: 0.3.7
Summary: A tool to create 2D morphology collage plots based on matplotlib.
Home-page: https://neurocollage.readthedocs.io
Author: Blue Brain Project, EPFL
License: Apache License 2.0
Project-URL: Tracker, https://github.com/BlueBrain/neurocollage/issues
Project-URL: Source, https://github.com/BlueBrain/neurocollage
Classifier: Development Status :: 2 - Pre-Alpha
Classifier: Intended Audience :: Education
Classifier: Intended Audience :: Science/Research
Classifier: Programming Language :: Python
Classifier: Programming Language :: Python :: 3
Classifier: Programming Language :: Python :: 3.9
Classifier: Programming Language :: Python :: 3.10
Classifier: Programming Language :: Python :: 3.11
Classifier: Programming Language :: Python :: 3.12
Classifier: Topic :: Scientific/Engineering :: Bio-Informatics
Requires-Python: >=3.9
License-File: LICENSE.txt
License-File: AUTHORS.md
Requires-Dist: bluepysnap >=3.0.1
Requires-Dist: brainbuilder >=0.20.1
Requires-Dist: click >=8
Requires-Dist: geomdl >=5.2.8
Requires-Dist: joblib >=1.1
Requires-Dist: mapbox-earcut >=1
Requires-Dist: matplotlib >=3.6
Requires-Dist: morph-tool >=2.9
Requires-Dist: networkx >=2.5
Requires-Dist: neurom >=3.2
Requires-Dist: numpy >=1.26
Requires-Dist: pandas >=2.1
Requires-Dist: pyglet <2,>=1.5.20
Requires-Dist: pyquaternion >=0.9.5
Requires-Dist: region-grower >=1.5.1
Requires-Dist: scikit-learn >=1.1
Requires-Dist: scipy >=1.13
Requires-Dist: tqdm >=4.60
Requires-Dist: trimesh >=3.23
Requires-Dist: voxcell >=3.1.5
Requires-Dist: vtk >=9.0.2
Provides-Extra: docs
Requires-Dist: docutils <0.21 ; extra == 'docs'
Requires-Dist: m2r2 ; extra == 'docs'
Requires-Dist: sphinx ; extra == 'docs'
Requires-Dist: sphinx-bluebrain-theme ; extra == 'docs'
Requires-Dist: sphinx-click ; extra == 'docs'
Provides-Extra: test
Requires-Dist: mock >=3 ; extra == 'test'
Requires-Dist: coverage <7,>=6.5 ; extra == 'test'
Requires-Dist: pytest >=6.1 ; extra == 'test'
Requires-Dist: pytest-click >=1.1 ; extra == 'test'
Requires-Dist: pytest-console-scripts >=1.4 ; extra == 'test'
Requires-Dist: pytest-cov >=4.1 ; extra == 'test'
Requires-Dist: pytest-html >=3.2 ; extra == 'test'
